ht_fix/__init__.py
ht_fix-0.1.6.dist-info/METADATA
ht_fix-0.1.6.dist-info/WHEEL
ht_fix-0.1.6.dist-info/RECORD
