Metadata-Version: 2.3
Name: ht-fix
Version: 0.1.6
Summary: Convert messy basketball height strings into inches; clamp outside 5–8 ft to NaN.
License: MIT
Author: Saurabh work.saurabhsabharwal@gmail.com
Requires-Python: >=3.9,<4.0
Classifier: License :: OSI Approved :: MIT License
Classifier: Programming Language :: Python :: 3
Classifier: Programming Language :: Python :: 3.9
Classifier: Programming Language :: Python :: 3.10
Classifier: Programming Language :: Python :: 3.11
Classifier: Programming Language :: Python :: 3.12
Classifier: Programming Language :: Python :: 3.13
